ferrolearn-0.1.0.dist-info/METADATA
ferrolearn-0.1.0.dist-info/WHEEL
ferrolearn/__init__.py
ferrolearn/ferrolearn.cpython-312-x86_64-linux-gnu.so
ferrolearn-0.1.0.dist-info/RECORD
